README.rst
setup.cfg
setup.py
PyQueueManager.egg-info/PKG-INFO
PyQueueManager.egg-info/SOURCES.txt
PyQueueManager.egg-info/dependency_links.txt
PyQueueManager.egg-info/not-zip-safe
PyQueueManager.egg-info/requires.txt
PyQueueManager.egg-info/top_level.txt
queue_manager/__init__.py
queue_manager/pubsub_consumer.py
queue_manager/pubsub_publisher.py
queue_manager/queue_manager.py
queue_manager/rabbitmq_consumer.py
queue_manager/rabbitmq_publisher.py
queue_manager/test_pubsub_consumer.py
queue_manager/test_pubsub_publisher.py
queue_manager/test_queue_manager.py
queue_manager/test_rabbitmq_consumer.py
queue_manager/test_rabbitmq_publisher.py
queue_manager/tornado_consumer.py