Metadata-Version: 2.1
Name: PyQueueManager
Version: 1.12.1
Summary: Library to deal with RabbitMQ and Google PubSub
Home-page: https://github.com/ateliedocodigo/py-queue-manager
Author: Luis Fernando Gomes
Author-email: luiscoms@ateliedocodigo.com.br
License: MIT
Download-URL: https://github.com/ateliedocodigo/py-queue-manager/tarball/1.12.1
Platform: any
Classifier: Development Status :: 5 - Production/Stable
Classifier: Programming Language :: Python :: 2.7
Classifier: Programming Language :: Python :: 3
Provides-Extra: rabbitmq
Provides-Extra: pubsub
